{
  "name": "JodaTimeConverterManager",
  "language": "java",
  "description": "Joda-Time's ConverterManager makes the semantics of DateTime/Instant/etc construction subject to global static state. If you need to define your own converters, use a helper.",
  "example": null,
  "cwe": null,
  "cwe-description": null,
  "checker-language": "java",
  "loc": 47,
  "branches": 1,
  "apis": 1,
  "test": [
    {
      "description": "converterManager",
      "expected-problems": null,
      "expected-linenumbers": [
        29
      ],
      "code": "import org.joda.time.convert.ConverterManager;\n\n            class Test {\n              // BUG: Diagnostic contains: JodaTimeConverterManager\n              ConverterManager cm = ConverterManager.getInstance();\n            }"
    },
    {
      "description": "withinJoda",
      "expected-problems": null,
      "expected-linenumbers": [
        45
      ],
      "code": "package org.joda.time;\n\n            import org.joda.time.convert.ConverterManager;\n\n            class Test {\n              ConverterManager cm = ConverterManager.getInstance();\n            }"
    }
  ]
}