{
  "name": "UtcDateUtils",
  "language": "java",
  "description": null,
  "example": null,
  "cwe": null,
  "cwe-description": null,
  "checker-language": "java",
  "loc": 16,
  "branches": 0,
  "apis": 7,
  "test": [
    {
      "description": "parse_then_format",
      "expected-problems": null,
      "expected-linenumbers": 4,
      "code": "  public void parse_then_format() {\n\n    Date date = UtcDateUtils.parseDateTime(\"2014-01-14T14:00:00+0200\");\n\n    assertThat(UtcDateUtils.formatDateTime(date)).isEqualTo(\"2014-01-14T12:00:00+0000\");\n\n  }"
    },
    {
      "description": "fail_if_bad_format",
      "expected-problems": null,
      "expected-linenumbers": 8,
      "code": "  public void fail_if_bad_format() {\n\n    try {\n\n      UtcDateUtils.parseDateTime(\"2014-01-14\");\n\n      fail();\n\n    } catch (IllegalArgumentException e) {\n\n      assertThat(e).hasMessage(\"Fail to parse date: 2014-01-14\");\n\n    }\n\n  }"
    }
  ]
}