{
  "name": "MultipleTopLevelClasses",
  "language": "java",
  "description": "Source files should not contain multiple top-level class declarations",
  "example": null,
  "cwe": null,
  "cwe-description": null,
  "checker-language": "java",
  "loc": 65,
  "branches": 7,
  "apis": 2,
  "test": [
    {
      "description": "twoClasses",
      "expected-problems": null,
      "expected-linenumbers": [
        33
      ],
      "code": "package a;\n\n            // BUG: Diagnostic contains: one top-level class declaration, instead found: One, Two\n            class One {}\n\n            // BUG: Diagnostic contains:\n            class Two {}"
    },
    {
      "description": "packageInfo",
      "expected-problems": null,
      "expected-linenumbers": [
        50
      ],
      "code": "/** Documentation for our package */\n            package a;"
    },
    {
      "description": "defaultPackage",
      "expected-problems": null,
      "expected-linenumbers": [
        62
      ],
      "code": "// BUG: Diagnostic contains:\n            class A {}\n\n            // BUG: Diagnostic contains:\n            class B {}"
    },
    {
      "description": "suppression",
      "expected-problems": null,
      "expected-linenumbers": [
        77
      ],
      "code": "package a;\n\n            class One {}\n\n            @SuppressWarnings(\"TopLevel\")\n            class Other {}"
    },
    {
      "description": "emptyDeclaration",
      "expected-problems": null,
      "expected-linenumbers": [
        93
      ],
      "code": "package a;\n\n            class Test {}\n            ;"
    },
    {
      "description": "semiInImportList",
      "expected-problems": null,
      "expected-linenumbers": [
        107
      ],
      "code": ""
    },
    {
      "description": "twoRecords",
      "expected-problems": null,
      "expected-linenumbers": [
        128
      ],
      "code": "package a;\n\n            // BUG: Diagnostic contains: one top-level class declaration, instead found: One, Two\n            record One() {}\n\n            // BUG: Diagnostic contains:\n            record Two() {}"
    }
  ]
}