{
  "name": "StaticMockMember",
  "language": "java",
  "description": "@Mock members of test classes shouldn't share state between tests and preferably be non-static",
  "example": null,
  "cwe": null,
  "cwe-description": null,
  "checker-language": "java",
  "loc": 59,
  "branches": 6,
  "apis": 1,
  "test": [
    {
      "description": "positiveCases",
      "expected-problems": null,
      "expected-linenumbers": [
        37
      ],
      "code": "import org.junit.runner.RunWith;\n            import org.junit.runners.JUnit4;\n            import org.mockito.Mock;\n\n            @RunWith(JUnit4.class)\n            public class Test {\n              @Mock private static String mockedPrivateString;\n              @Mock static String mockedString;\n            }\n            \n\n            import org.junit.runner.RunWith;\n            import org.junit.runners.JUnit4;\n            import org.mockito.Mock;\n\n            @RunWith(JUnit4.class)\n            public class Test {\n              @Mock private String mockedPrivateString;\n              @Mock String mockedString;\n            }"
    },
    {
      "description": "negativeCases",
      "expected-problems": null,
      "expected-linenumbers": [
        69
      ],
      "code": "import org.junit.runner.RunWith;\n            import org.junit.runners.JUnit4;\n            import org.mockito.Mock;\n\n            @RunWith(JUnit4.class)\n            public class Test {\n              @Mock private String mockedPrivateString;\n              @Mock String mockedString;\n            }"
    },
    {
      "description": "memberSuppression",
      "expected-problems": null,
      "expected-linenumbers": [
        88
      ],
      "code": "import org.junit.runner.RunWith;\n            import org.junit.runners.JUnit4;\n            import org.mockito.Mock;\n\n            @RunWith(JUnit4.class)\n            public class Test {\n              @SuppressWarnings(\"StaticMockMember\")\n              @Mock\n              private static String mockedPrivateString;\n            }"
    },
    {
      "description": "flagIfRemovingStaticWontCompile",
      "expected-problems": null,
      "expected-linenumbers": [
        108
      ],
      "code": "import org.junit.runner.RunWith;\n            import org.junit.runners.JUnit4;\n            import org.mockito.Mock;\n\n            @RunWith(JUnit4.class)\n            public class Test {\n              // BUG: Diagnostic contains: StaticMockMember\n              @Mock private static String mockedPrivateString;\n\n              static String someStaticMethod() {\n                return mockedPrivateString;\n              }\n            }"
    }
  ]
}