{
  "tool": {
    "name": "Clang-Tidy",
    "version": "17.0.6",
    "languages": ["C", "C++"],
    "license": "Apache-2.0",
    "repository": "https://github.com/llvm/llvm-project",
    "homepage": "https://clang.llvm.org/extra/clang-tidy/",
    "description": "Clang-Tidy is a clang-based C++ linter tool.",
    "last_updated": "2025-06-30"
  },
  "rules_summary": {
    "total_rules": 435,
    "categories": [
      "readability", "performance", "modernize", "bugprone", "clang-analyzer"
    ]
  }
}
